rotaeno/__init__.py
rotaeno/ai.py
rotaeno/config.py
rotaeno/database.py
rotaeno/getInfo.py
rotaeno/getProcessedData.py
rotaeno/utils.py
rotaeno/assets/html/b40.html
rotaeno/assets/html/friend_code.html
rotaeno/assets/html/friend_info.html
rotaeno/assets/html/friend_song_score_ranking.html
rotaeno/assets/html/me_info.html
rotaeno/assets/html/song.html
rotaeno/assets/html/song_ratingreal_range.html
rotaeno/assets/html/songs_status.html
rotaeno/assets/html/user_ranking.html
rotaeno/db/songAlias.db
rotaeno/db/songs.db
rotaeno/model/score_predictor.pth
rotaeno-0.1.1.dist-info/LICENSE
rotaeno-0.1.1.dist-info/METADATA
rotaeno-0.1.1.dist-info/WHEEL
rotaeno-0.1.1.dist-info/top_level.txt
rotaeno-0.1.1.dist-info/RECORD
