Metadata-Version: 2.2
Name: rotaeno
Version: 0.1.1
Summary: A Rotaeno Official Python Package
Author-email: None1145 <none@nonewiki.top>
Project-URL: Homepage, https://rotaeno.nonewiki.top/info
Project-URL: Issues, https://github.com/None1145
Classifier: Programming Language :: Python :: 3
Classifier: Operating System :: OS Independent
Classifier: License :: OSI Approved :: MIT License
Requires-Python: >=3.6
License-File: LICENSE
Requires-Dist: torch
Requires-Dist: numpy
Requires-Dist: thefuzz
Requires-Dist: scipy
Requires-Dist: selenium
Requires-Dist: matplotlib
